matrix_manipulation/__init__.py
matrix_manipulation/module.py
matrix_manipulation_abd-0.0.1.dist-info/METADATA
matrix_manipulation_abd-0.0.1.dist-info/WHEEL
matrix_manipulation_abd-0.0.1.dist-info/top_level.txt
matrix_manipulation_abd-0.0.1.dist-info/RECORD
